LICENSE
MANIFEST.in
setup.cfg
setup.py
tap_clubhouse/__init__.py
tap_clubhouse/utils.py
tap_clubhouse.egg-info/PKG-INFO
tap_clubhouse.egg-info/SOURCES.txt
tap_clubhouse.egg-info/dependency_links.txt
tap_clubhouse.egg-info/entry_points.txt
tap_clubhouse.egg-info/requires.txt
tap_clubhouse.egg-info/top_level.txt
tap_clubhouse/schemas/epics.json
tap_clubhouse/schemas/projects.json
tap_clubhouse/schemas/stories.json
tap_clubhouse/schemas/users.json
tap_clubhouse/schemas/workflows.json