Metadata-Version: 1.1
Name: tap-clubhouse
Version: 0.2.0
Summary: Singer.io tap for extracting data from the Clubhouse API
Home-page: http://singer.io
Author: Kamal Mahyuddin
Author-email: kamal@envoy.com
License: UNKNOWN
Download-URL: https://github.com/envoy/tap-clubhouse/archive/0.2.0.tar.gz
Platform: UNKNOWN
Classifier: Programming Language :: Python :: 3 :: Only
